stockhub/__init__.py
stockhub/zztemp.py
stockhub-0.0.1.dist-info/LICENSE
stockhub-0.0.1.dist-info/METADATA
stockhub-0.0.1.dist-info/WHEEL
stockhub-0.0.1.dist-info/top_level.txt
stockhub-0.0.1.dist-info/RECORD
